dashboard_data/__init__.py
dashboard_data/metrics_tables.py
dashboard_data/rainfall_data_explorer.py
dashboard_data/spw_explorer.py
dashboard_data/spw_metrics_tables.py
jobs/__init__.py
jobs/job_utils.py
jobs/run_all_metrics.py
jobs/run_biweekly_table_metrics.py
jobs/run_forecasts.py
jobs/run_grouped_metrics.py
jobs/run_seasonal_table_metrics.py
jobs/run_spatial_metrics.py
jobs/run_station_table_metrics.py
jobs/run_table_metrics.py
sheerwater/__init__.py
sheerwater/climatology.py
sheerwater/metrics.py
sheerwater/metrics_library.py
sheerwater/nuthatch.toml
sheerwater/regions_and_masks.py
sheerwater/statistics_library.py
sheerwater/data/README.md
sheerwater/data/__init__.py
sheerwater/data/chirps.py
sheerwater/data/ghcn.py
sheerwater/data/imerg.py
sheerwater/data/tahmo.py
sheerwater/forecasts/__init__.py
sheerwater/forecasts/ecmwf_er.py
sheerwater/forecasts/ecmwf_er_iri.py
sheerwater/forecasts/fuxi.py
sheerwater/forecasts/gencast.py
sheerwater/forecasts/graphcast.py
sheerwater/forecasts/salient.py
sheerwater/interfaces/__init__.py
sheerwater/interfaces/datasets.py
sheerwater/interfaces/spatial.py
sheerwater/reanalysis/__init__.py
sheerwater/reanalysis/cbam.py
sheerwater/reanalysis/era5.py
sheerwater/reanalysis/era5_cds.py
sheerwater/tasks/__init__.py
sheerwater/tasks/spw.py
sheerwater/tests/conftest.py
sheerwater/tests/test_climatology.py
sheerwater/tests/test_forecasts.py
sheerwater/tests/test_grouped_metrics_performance.py
sheerwater/tests/test_metric_correctness.py
sheerwater/tests/test_metrics.py
sheerwater/tests/test_precip_range.py
sheerwater/tests/test_regions_and_masks.py
sheerwater/tests/test_target_dates.py
sheerwater/tests/test_utils.py
sheerwater/utils/__init__.py
sheerwater/utils/data_utils.py
sheerwater/utils/forecaster_utils.py
sheerwater/utils/general_utils.py
sheerwater/utils/grouping_utils.py
sheerwater/utils/region_utils.py
sheerwater/utils/remote.py
sheerwater/utils/secrets.py
sheerwater/utils/space_utils.py
sheerwater/utils/task_utils.py
sheerwater-0.2.5.dist-info/METADATA
sheerwater-0.2.5.dist-info/WHEEL
sheerwater-0.2.5.dist-info/licenses/LICENSE
sheerwater-0.2.5.dist-info/RECORD
