Metadata-Version: 2.3
Name: sheerwater
Version: 0.2.5
Summary: Africa-first library for data, forecasts, and benchmarking.
Author-email: Genevieve Flaspohler <genevieve@rhizaresearch.org>, Joshua Adkins <josh@rhizaresearch.org>
License: MIT
Requires-Python: >=3.12
Requires-Dist: bokeh
Requires-Dist: cdsapi>=0.7.3
Requires-Dist: click
Requires-Dist: coiled>=1.76.1
Requires-Dist: cryptography
Requires-Dist: dask
Requires-Dist: dask[complete]
Requires-Dist: dateparser
Requires-Dist: ecmwf-api-client
Requires-Dist: flox
Requires-Dist: gcsfs
Requires-Dist: geopandas
Requires-Dist: google-api-python-client
Requires-Dist: google-cloud-secret-manager
Requires-Dist: google-cloud-storage
Requires-Dist: h5netcdf
Requires-Dist: h5py
Requires-Dist: httplib2
Requires-Dist: huggingface-hub
Requires-Dist: matplotlib
Requires-Dist: minio
Requires-Dist: netcdf4
Requires-Dist: numcodecs<0.16.0
Requires-Dist: numpy
Requires-Dist: nuthatch
Requires-Dist: opt-einsum>=3.4.0
Requires-Dist: plotly>=5.24.1
Requires-Dist: properscoring
Requires-Dist: py7zr
Requires-Dist: pyzstd==0.16.2
Requires-Dist: requests
Requires-Dist: rioxarray
Requires-Dist: s3fs
Requires-Dist: scikit-learn
Requires-Dist: scipy
Requires-Dist: tqdm
Requires-Dist: xarray-regrid
Requires-Dist: xarray==2025.1.0
Requires-Dist: zarr==2.18.3
